{
  "id": "12641",
  "title": "Penggunaan abu sekam padi dan kapur sebagai campuran sirtu dalam pembuatan urugan ringan",
  "abstract": "Suatu timbunan akan mengalami kelongsoran apabila diurug secara cepat, hal ini disebabkan karena berat sendiri timbunan yang cukup besar. Oleh sebab itu digunakan bahan alternatif yang memiliki berat sendiri yang ringan sebagai bahan campuran dari tanah timbunan. Dalam hal ini digunakan abu sekam padi sebagai bahan campuran sirtu dan kapur sebagai bahan pengikatnya. Tujuan penelitian ini mencari perbandingan yang ideal dari abu sekam padi, kapur dan sirtu. Yang dimaksud ideal dalam hal ini adalah bukan saja didapatkan suatu perbandingan yang tidak hanya ringan tetapi mempunyai kekuatan yang cukup untuk menerima beban struktural diatasnya tanpa menimbulkan proses kelongsoran. Variabel yang dicari dalam penelitian ini adalah harga y, nilai CBR dan harga Creators SUWANDI POLLES; TONY YONGNARDI Contributors Johanes Indrojono Suwono (Advisor 1); Jonathan Hendra Kusuma (Examination Committee 1) Publisher Universitas Kristen Petra Language Indonesian Theme Digital Theses Category Undergraduate Thesis Sub category Skripsi/Undergraduate Thesis Source Skripsi No. 928 S; Tony Yongnardi (21494111), Suwandi Polles (21494144) Subjects SOIL MECHANICS; SOIL STABILIZATION Files Cover pdf 2.1 MB Abstract TOC pdf 665 KB Chapter 1 pdf 528 KB Chapter 2 pdf 705 KB Chapter 3 pdf 443 KB Chapter 4 pdf 2.5 MB Conclusion pdf 213 KB References pdf 163 KB Appendices pdf 3.3 MB",
  "creators": "SUWANDI POLLES; TONY YONGNARDI",
  "contributors": "Johanes Indrojono Suwono (Advisor 1); Jonathan Hendra Kusuma (Examination Committee 1)",
  "publisher": "Universitas Kristen Petra",
  "language": "Indonesian",
  "theme": "Digital Theses",
  "category": "Undergraduate Thesis",
  "sub_category": "Skripsi/Undergraduate Thesis",
  "source": "Skripsi No. 928 S; Tony Yongnardi (21494111), Suwandi Polles (21494144)",
  "subjects": "SOIL MECHANICS; SOIL STABILIZATION"
}