{
  "id": "18087",
  "title": "Pengaruh kemiringan dinding pondasi tiang pendek terhadap peningkatan daya dukungnya",
  "abstract": "Pondasi yang umum digunakan pada proyek-proyek rumah tinggal adalah pondasi batu kali menerus yang umumnya dikerjakan dengan bantuan orang banyak dan membutuhkan waktu lama. Dalam penelitian ini dikembangkan suatu pondasi tiang pendek berbentuk kerucut terpancung dengan pemancangan menggunakan metode jacking dan metode hammer. Dimana Dasar pemikiran pondasi ini adalah pondasi \"tapered pile\" yang telah dikenal diluar negeri Dengan bentuk ini tanah pada dinding tiang akan memberikan dukungan terhadap gaya yang bekerja bukan sebagai gesekan tetapi sebagai bearing. Kemiringan dinding pondasi tiang pendek bentuk ini dapat lebih menghemat penggunaan material dan meningkatkan daya dukung pondasi. Penelitian yang dilakukan pada Laboratorium Mekanika Tanah Universitas Kristen Petra ini menggunakan beberapa sampel model pondasi yang berbentuk kerucut terpancung dengan diameter atas ditentukan 4.2 cm dan diameter bawah dibuat bervariasi sebagai kemiringan sudut: 4,2 cm (00= 0?); 3 cm (?= 2?) ; 2,5 cm (?= 4?) ; 2 cm (co= 5?) ; 1,5 cm (co=6?). Model pondasi dipancang pada tanah liat lunak dengan metode jacking dan metode hammer. Hasil penelitian menunjukan bahwa adanya kemiringan pada dinding pondasi tiang pendek memiliki daya dukung yang lebih besar daripada pondasi tiang yang berbentuk lurus tanpa kemiringan dinding tiang ( Creators AGUSTINUS YOPI WIDYA WIRA; FIRMAN AHMAD PAMUNGKAS Contributors Benjamin Lumantarna (Examination Committee 1); Sugie Prawono (Advisor 1) Publisher Universitas Kristen Petra Language Indonesian Theme Digital Theses Category Undergraduate Thesis Sub category Skripsi/Undergraduate Thesis Source Skripsi No. 877 S; Agustinus Yopi (21492225), Firman A. Pamungkas (21493179) Subjects FOUNDATIONS; SOIL MECHANICS Files Cover pdf 560 KB Abstract TOC pdf 2.2 MB Chapter 1 pdf 576 KB Chapter 2 pdf 1.7 MB Chapter 3 pdf 2.2 MB Chapter 4 pdf 5.1 MB Chapter 5 pdf 1.9 MB Conclusion pdf 274 KB References pdf 262 KB Appendices pdf 3.1 MB",
  "creators": "AGUSTINUS YOPI WIDYA WIRA; FIRMAN AHMAD PAMUNGKAS",
  "contributors": "Benjamin Lumantarna (Examination Committee 1); Sugie Prawono (Advisor 1)",
  "publisher": "Universitas Kristen Petra",
  "language": "Indonesian",
  "theme": "Digital Theses",
  "category": "Undergraduate Thesis",
  "sub_category": "Skripsi/Undergraduate Thesis",
  "source": "Skripsi No. 877 S; Agustinus Yopi (21492225), Firman A. Pamungkas (21493179)",
  "subjects": "FOUNDATIONS; SOIL MECHANICS"
}