{
  "id": "23985",
  "title": "Perencanaan dan pembuatan pengebor PCB yang dapat diprogram melalui komputer IBM PC",
  "abstract": "Peralatan pengebor PCB irli b+rguna untuk n~embant~u pelaksanaan proses penge1:)oran parrla FCR yang bersif at, masal . Ferala.t,an pengebor PCB yang dapat, d.iprogram melalui ko~nput,er IBM F'C ini dihuat unt.uk dapat n~elaksanakan pr70ses pen.gebor7an secara ot.o~nat.iu n~elalui rneltarlik yang dapat, cliliontr-o 1 o leh komput~er dengall data y3.r-g c~liambil dari file data PCB p~t.o;~an~ Fr~t~el. Per%alat.an . pensebor PCR ini didesain cleilgall mcnggunalian parale1 p(21.t~ pada licmputer unt,uk rnendayagunalcan pe~-al;t t.an stanilal~ pacla lio~nput~er. Pr~2gra1n yang dibuat pada peralat.an pangebor PCB ini men~gunalcan hahasa pemrograman Turbo Pascal 7 -0 yang berguna unt Creators GUNAWAN Contributors NAWANTO WIBOWO (Examination Committee 1); HERLIANTO TENGGARA (Advisor 1); Rolly Intan (Advisor 2) Publisher Universitas Kristen Petra Language Indonesian Theme Digital Theses Category Undergraduate Thesis Sub category Skripsi/Undergraduate Thesis Source Skripsi No. 96/E/EL/038/298; Gunawan (23491087) Subjects DRILLING AND BORING MACHINERY; DRILLING AND BORING-COMPUTER PROGRAMS Files Cover pdf 101 KB Abstract TOC pdf 174 KB Chapter 1 pdf 118 KB Chapter 2 pdf 251 KB Chapter 3 pdf 110 KB Chapter 4 pdf 116 KB Chapter 5 pdf 137 KB Chapter 6 pdf 658 KB Chapter 7 pdf 209 KB Conclusion pdf 68 KB References pdf 24 KB Appendices pdf 384 KB",
  "creators": "GUNAWAN",
  "contributors": "NAWANTO WIBOWO (Examination Committee 1); HERLIANTO TENGGARA (Advisor 1); Rolly Intan (Advisor 2)",
  "publisher": "Universitas Kristen Petra",
  "language": "Indonesian",
  "theme": "Digital Theses",
  "category": "Undergraduate Thesis",
  "sub_category": "Skripsi/Undergraduate Thesis",
  "source": "Skripsi No. 96/E/EL/038/298; Gunawan (23491087)",
  "subjects": "DRILLING AND BORING MACHINERY; DRILLING AND BORING-COMPUTER PROGRAMS"
}