{
  "id": "30473",
  "title": "Analisis pengaruh input panas pada pengelasan stainless steel dengan GMAW terhadap derajat dan luas daerah presipitasi",
  "abstract": "Adanya daerah yang terpengaruh panas atau HAZ sangat perlu diperhatikan dalam suatu proses pengelasan. Dalam suatu pengelasan baja tahan karat AISI 304 walaupun mempunyai sifat weldability yang baik, tetapi akan timbul daerah presipitasi. Hal ini disebabkan oleh adanya senyawa karbida chrom yang terbentuk pada batas butir. Daerah presipitasi ini terbentuk pada temperatur 420°C-871°C. Dengan terjadinya presipitasi ini maka akan menurunkan sifat tahan korosi baja tahan karat AISI 304. Penelitian ini dilakukan untuk melihat derajat dan luas daerah presipitasi, bila input panas dan laju pendinginan pengelasan diubah. Dari hasil analisis menunjukkan perubahan derajat dan luas daerah presipitasi, di mana dengan pengelasan arus 80A Creators GUNAR PRIJANTORO Contributors Herry Sunandar (Advisor 2); MUSAIKAN (Advisor and Examination Committee) Publisher Universitas Kristen Petra Language Indonesian Theme Digital Theses Category Undergraduate Thesis Sub category Skripsi/Undergraduate Thesis Source Skripsi No. ...; Gunar Prijantoro (24490004) Subjects WELDING INDUSTRY-QUALITY CONTROL; ELECTRIC WELDING Files Cover pdf 233 KB Abstract TOC pdf 410 KB Chapter 1 pdf 298 KB Chapter 2 pdf 2 MB Chapter 3 pdf 417 KB Chapter 4 pdf 3.5 MB Chapter 5 pdf 353 KB Conclusion pdf 170 KB References pdf 170 KB Appendices pdf 414 KB",
  "creators": "GUNAR PRIJANTORO",
  "contributors": "Herry Sunandar (Advisor 2); MUSAIKAN (Advisor and Examination Committee)",
  "publisher": "Universitas Kristen Petra",
  "language": "Indonesian",
  "theme": "Digital Theses",
  "category": "Undergraduate Thesis",
  "sub_category": "Skripsi/Undergraduate Thesis",
  "source": "Skripsi No. ...; Gunar Prijantoro (24490004)",
  "subjects": "WELDING INDUSTRY-QUALITY CONTROL; ELECTRIC WELDING"
}