{
  "id": "46621",
  "title": "Analisa persepsi keadilan penanganan complaint, word of mouth, dan kepuasan terhadap minat pembelian kembali: studi pada cafe di Surabaya",
  "abstract": "Penelitian ini dilakukan di cafe-cafe yang terdapat pada tiga mall di Surabaya yaitu Galaxy Mall, Tunjungan Plasa, dan Surabaya Town Square. Peneliti mengambil sampel sebanyak 405 responden dari populasi yang tidak terbatas {infinite). Adapun tujuan yang ingin dicapai dalam penelitian ini adalah untuk mengetahui pengaruh persepsi keadilan berdasarkan penanganan complaint, word o f mouth, dan kepuasan terhadap minat pembelian kembali pada cafe-cafe di Surabaya. Berdasarkan hasil penelitian diperoleh bahwa Persepsi keadilan penanganan complaint berpengaruh positif terhadap WOM Dissemination dan WOM V Creators SHERLY FLORENSIA; BERNADETHA RINA JAYA Contributors Hatane Semuel (Advisor and Examination Committee); Fransisca Andreani (Advisor 2) Publisher Universitas Kristen Petra Language Indonesian Theme Digital Theses Category Undergraduate Thesis Sub category Skripsi/Undergraduate Thesis Source Skripsi No. 33010086/MAN/2010; Sherly Florensia (33405075), Bemadetha Rina Jaya (33405115) Subjects HOTEL MANAGEMENT; CONSUMER BEHAVIOR--CASE STUDIES; HOTELS--MARKETING Files Cover pdf 205 KB Abstract TOC pdf 727 KB Chapter 1 pdf 292 KB Chapter 2 pdf 684 KB Chapter 3 pdf 521 KB Chapter 4 pdf 1.2 MB Conclusion pdf 158 KB References pdf 148 KB Appendices pdf 1 MB",
  "creators": "SHERLY FLORENSIA; BERNADETHA RINA JAYA",
  "contributors": "Hatane Semuel (Advisor and Examination Committee); Fransisca Andreani (Advisor 2)",
  "publisher": "Universitas Kristen Petra",
  "language": "Indonesian",
  "theme": "Digital Theses",
  "category": "Undergraduate Thesis",
  "sub_category": "Skripsi/Undergraduate Thesis",
  "source": "Skripsi No. 33010086/MAN/2010; Sherly Florensia (33405075), Bemadetha Rina Jaya (33405115)",
  "subjects": "HOTEL MANAGEMENT; CONSUMER BEHAVIOR--CASE STUDIES; HOTELS--MARKETING"
}