{
  "id": "53723",
  "title": "Efektivitas penggunaan lifni sanders sebagai celebrity endorser dalam peluncuran 4 shades cushion di akun instagram @somethincofficial",
  "abstract": "Berlatar dari kritikan Lifni Sanders dan sebagian besar masyarakat Indonesia mengenai stigma standar kecantikan di Indonesia yang dikonstruksi oleh media sosial sekaligus banyaknya cushion yang beredar baik dari dalam maupun luar negeri, Somethinc hadirkan cushion dengan 4 shades terbaru pada salah satu produknya yang dinamakan ‘Copy Paste Breathable Mesh Cushion’. Somethinc berkolaborasi dengan Lifni Sanders, yakni seorang beauty vloggers asal Papua yang sudah terjun dalam industri kecantikan sejak tahun 2013. Dikarenakan tidak semua endorsement pasti mendapatkan feedback yang sepadan dengan biaya yang dikeluarkan, maka penting bagi perusahaan untuk mengevaluasi celebrity endorser yang telah digunakan dalam menyampaikan pesan iklan di media sosial. Efektivitas celebrity endorser dalam penelitian ini diukur dengan menggunakan model TEARS menurut Shimp (2006), yakni Trustworthiness, Expertise, Attractiveness, Respect, dan Similarity. Jenis penelitian ini merupakan penelitian kuantitatif deskriptif, dengan menggunakan metode survei. Survei yang disebarkan secara online telah dilakukan pada 397 responden sesuai dengan kriteria. Hasil penelitian ini menunjukkan bahwa bahwa penggunaan Lifni Sanders sebagai celebrity endorser dalam peluncuran 4 shades terbaru ‘Copy Paste Breathable Mesh Cushion’ Somethinc di akun Instagram @somethincofficial dapat dinyatakan efektif karena berada pada rentang skala 3.10 Creators GWYNETH AUDREY Contributors Dr. Inri Inggrit Indrayani, S.I.P., M.Si. (Advisor 1); Astri Yogatama (Advisor 2); Gatut Priyowidodo (Examination Committee 1) Publisher Universitas Kristen Petra Language Indonesian Theme Digital Theses Category Undergraduate Thesis Sub category Skripsi/Undergraduate Thesis Source Skripsi No. 10011772/KOM/2022; Gwyneth Audrey (F11180038) Subjects ADVERTISING; CONSUMER BEHAVIOR; ENDORSEMENTS IN ADVERTISING; INTERNET PERSONALITIES Files Cover pdf 527 KB Abstract TOC pdf 300 KB Chapter 1 pdf 784 KB Chapter 2 pdf 327 KB Chapter 3 pdf 288 KB Chapter 4 pdf 1 MB Conclusion pdf 136 KB References pdf 224 KB Appendices pdf 707 KB",
  "creators": "GWYNETH AUDREY",
  "contributors": "Dr. Inri Inggrit Indrayani, S.I.P., M.Si. (Advisor 1); Astri Yogatama (Advisor 2); Gatut Priyowidodo (Examination Committee 1)",
  "publisher": "Universitas Kristen Petra",
  "language": "Indonesian",
  "theme": "Digital Theses",
  "category": "Undergraduate Thesis",
  "sub_category": "Skripsi/Undergraduate Thesis",
  "source": "Skripsi No. 10011772/KOM/2022; Gwyneth Audrey (F11180038)",
  "subjects": "ADVERTISING; CONSUMER BEHAVIOR; ENDORSEMENTS IN ADVERTISING; INTERNET PERSONALITIES"
}